bigkinds/__init__.py
bigkinds/article_scraper.py
bigkinds/client.py
bigkinds/models.py
bigkinds/searcher.py
bigkinds_mcp/__init__.py
bigkinds_mcp/remote_server.py
bigkinds_mcp/server.py
bigkinds_mcp/core/__init__.py
bigkinds_mcp/core/async_client.py
bigkinds_mcp/core/async_scraper.py
bigkinds_mcp/core/cache.py
bigkinds_mcp/core/circuit_breaker.py
bigkinds_mcp/core/progress.py
bigkinds_mcp/core/rate_limiter.py
bigkinds_mcp/core/remote_cache.py
bigkinds_mcp/core/schema_validator.py
bigkinds_mcp/formatters/__init__.py
bigkinds_mcp/formatters/article.py
bigkinds_mcp/formatters/search.py
bigkinds_mcp/formatters/utility.py
bigkinds_mcp/formatters/visualization.py
bigkinds_mcp/models/__init__.py
bigkinds_mcp/models/schemas.py
bigkinds_mcp/prompts/__init__.py
bigkinds_mcp/prompts/analysis.py
bigkinds_mcp/resources/__init__.py
bigkinds_mcp/resources/news.py
bigkinds_mcp/tools/__init__.py
bigkinds_mcp/tools/analysis.py
bigkinds_mcp/tools/article.py
bigkinds_mcp/tools/search.py
bigkinds_mcp/tools/timeline_utils.py
bigkinds_mcp/tools/utils.py
bigkinds_mcp/tools/visualization.py
bigkinds_mcp/utils/__init__.py
bigkinds_mcp/utils/errors.py
bigkinds_mcp/utils/errors_kr.py
bigkinds_mcp/utils/image_filter.py
bigkinds_mcp/utils/markdown.py
bigkinds_mcp/validation/__init__.py
bigkinds_mcp/validation/date_validator.py
bigkinds_mcp/visualization/__init__.py
bigkinds_mcp/visualization/chart_formatter.py
bigkinds_mcp/visualization/comparison_formatter.py
bigkinds_mcp/visualization/heatmap_formatter.py
bigkinds_mcp/visualization/timeline_formatter.py
bigkinds_mcp/visualization/wordcloud_formatter.py
bigkinds_mcp-3.0.0.dist-info/METADATA
bigkinds_mcp-3.0.0.dist-info/WHEEL
bigkinds_mcp-3.0.0.dist-info/entry_points.txt
bigkinds_mcp-3.0.0.dist-info/RECORD
