Metadata-Version: 2.4
Name: bigkinds-mcp
Version: 3.0.0
Summary: BigKinds News MCP Server - Korean news search, analysis, and visualization
Project-URL: Homepage, https://github.com/seolcoding/bigkinds-mcp
Project-URL: Repository, https://github.com/seolcoding/bigkinds-mcp
Project-URL: Issues, https://github.com/seolcoding/bigkinds-mcp/issues
Author-email: seolcoding <seolcoding@gmail.com>
License-Expression: MIT
Keywords: bigkinds,claude,data-journalism,korean-news,llm,mcp,news-search,news-visualization
Classifier: Development Status :: 4 - Beta
Classifier: Intended Audience :: Developers
Classifier: License :: OSI Approved :: MIT License
Classifier: Programming Language :: Python :: 3
Classifier: Programming Language :: Python :: 3.12
Classifier: Programming Language :: Python :: 3.13
Classifier: Topic :: Software Development :: Libraries :: Python Modules
Classifier: Topic :: Text Processing :: General
Requires-Python: >=3.12
Requires-Dist: beautifulsoup4>=4.12.0
Requires-Dist: cachetools>=5.0.0
Requires-Dist: httpx>=0.27.0
Requires-Dist: kiwipiepy>=0.18.0
Requires-Dist: markdownify>=0.14.1
Requires-Dist: mcp>=1.0.0
Requires-Dist: pandas>=2.0.0
Requires-Dist: pydantic>=2.0.0
Requires-Dist: requests>=2.31.0
Provides-Extra: dev
Requires-Dist: pytest-asyncio>=0.23.0; extra == 'dev'
Requires-Dist: pytest-cov>=6.0.0; extra == 'dev'
Requires-Dist: pytest-mock>=3.14.0; extra == 'dev'
Requires-Dist: pytest>=8.0.0; extra == 'dev'
Requires-Dist: respx>=0.22.0; extra == 'dev'
Provides-Extra: remote
Requires-Dist: fastapi>=0.115.0; extra == 'remote'
Requires-Dist: redis>=5.0.0; extra == 'remote'
Requires-Dist: uvicorn[standard]>=0.32.0; extra == 'remote'
